Metadata-Version: 2.1
Name: sqlite-utils-litecli
Version: 0.1.1
Summary: Interactive shell using litecli
Author: Simon Willison
License: Apache-2.0
Project-URL: Homepage, https://github.com/simonw/sqlite-utils-litecli
Project-URL: Changelog, https://github.com/simonw/sqlite-utils-litecli/releases
Project-URL: Issues, https://github.com/simonw/sqlite-utils-litecli/issues
Project-URL: CI, https://github.com/simonw/sqlite-utils-litecli/actions
Classifier: License :: OSI Approved :: Apache Software License
License-File: LICENSE
Requires-Dist: sqlite-utils
Requires-Dist: litecli
Provides-Extra: test
Requires-Dist: pytest ; extra == 'test'
